yes/__init__.py
yes/configuration.py
yes/documents.py
yes/errors.py
yes/flow.py
yes/hashes.py
yes/session.py
pyyes-0.2.0.dist-info/LICENSE
pyyes-0.2.0.dist-info/WHEEL
pyyes-0.2.0.dist-info/METADATA
pyyes-0.2.0.dist-info/RECORD
