Metadata-Version: 2.1
Name: pyyes
Version: 0.2.0
Summary: yes® Relying Party/Client Implementation in Python 3
License: MIT
Author: Daniel Fett
Author-email: danielf@yes.com
Requires-Python: >=3.8,<4.0
Classifier: License :: OSI Approved :: MIT License
Classifier: Programming Language :: Python :: 3
Classifier: Programming Language :: Python :: 3.10
Classifier: Programming Language :: Python :: 3.8
Classifier: Programming Language :: Python :: 3.9
Requires-Dist: PyJWT (>=2.2.0,<3.0.0)
Requires-Dist: cryptography (>=35.0.0,<36.0.0)
Requires-Dist: furl (>=2.1.3,<3.0.0)
Requires-Dist: pyHanko[pkcs11] (==0.8.0)
